arlas_tagger_api_python/__init__.py
arlas_tagger_api_python/api_client.py
arlas_tagger_api_python/configuration.py
arlas_tagger_api_python/rest.py
arlas_tagger_api_python/apis/__init__.py
arlas_tagger_api_python/apis/status_api.py
arlas_tagger_api_python/apis/write_api.py
arlas_tagger_api_python/models/__init__.py
arlas_tagger_api_python/models/error.py
arlas_tagger_api_python/models/expression.py
arlas_tagger_api_python/models/failure.py
arlas_tagger_api_python/models/filter.py
arlas_tagger_api_python/models/form.py
arlas_tagger_api_python/models/page.py
arlas_tagger_api_python/models/projection.py
arlas_tagger_api_python/models/propagation.py
arlas_tagger_api_python/models/search.py
arlas_tagger_api_python/models/tag.py
arlas_tagger_api_python/models/tag_ref_request.py
arlas_tagger_api_python/models/tag_request.py
arlas_tagger_api_python/models/update_response.py
test/__init__.py
test/test_error.py
test/test_expression.py
test/test_failure.py
test/test_filter.py
test/test_form.py
test/test_page.py
test/test_projection.py
test/test_propagation.py
test/test_search.py
test/test_status_api.py
test/test_tag.py
test/test_tag_ref_request.py
test/test_tag_request.py
test/test_update_response.py
test/test_write_api.py
arlas_tagger_api-24.1.0.dist-info/METADATA
arlas_tagger_api-24.1.0.dist-info/WHEEL
arlas_tagger_api-24.1.0.dist-info/top_level.txt
arlas_tagger_api-24.1.0.dist-info/RECORD
